{
  "usage": {
    "text_units": 1,
    "text_characters": 1272,
    "features": 1
  },
  "language": "es",
  "keywords": [
    {
      "text": "RICHARD GONZALEZ PRADO",
      "relevance": 0.753484,
      "count": 1
    },
    {
      "text": "PAGO DE vIATICOS",
      "relevance": 0.674641,
      "count": 1
    },
    {
      "text": "Consejo Superior",
      "relevance": 0.596406,
      "count": 1
    },
    {
      "text": "salidas de campo",
      "relevance": 0.574239,
      "count": 1
    },
    {
      "text": "pago de los vidticos",
      "relevance": 0.571924,
      "count": 1
    },
    {
      "text": "Florida Km",
      "relevance": 0.559548,
      "count": 1
    },
    {
      "text": "PESOS MCTE",
      "relevance": 0.546287,
      "count": 1
    },
    {
      "text": "Valle del Cauca",
      "relevance": 0.529576,
      "count": 1
    },
    {
      "text": "CUAL",
      "relevance": 0.525423,
      "count": 1
    },
    {
      "text": "San Antonio",
      "relevance": 0.521742,
      "count": 1
    },
    {
      "text": "valor total",
      "relevance": 0.521742,
      "count": 1
    },
    {
      "text": "DECANO DE LA FACULTAD DE INGENIERIA",
      "relevance": 0.517103,
      "count": 1
    },
    {
      "text": "uso de sus facultades legales",
      "relevance": 0.489828,
      "count": 1
    },
    {
      "text": "Estatuto General de la Universidad",
      "relevance": 0.48363,
      "count": 1
    },
    {
      "text": "PAGO DE VIATICOS A",
      "relevance": 0.479544,
      "count": 1
    },
    {
      "text": "Articulo",
      "relevance": 0.477103,
      "count": 1
    },
    {
      "text": "Curso de Ingenieria de Riegos IT",
      "relevance": 0.476839,
      "count": 1
    },
    {
      "text": "Cali",
      "relevance": 0.473779,
      "count": 1
    },
    {
      "text": "Caballeros",
      "relevance": 0.473295,
      "count": 1
    },
    {
      "text": "Escuela",
      "relevance": 0.466022,
      "count": 1
    },
    {
      "text": "pago",
      "relevance": 0.46346,
      "count": 1
    },
    {
      "text": "Universidad",
      "relevance": 0.462513,
      "count": 1
    },
    {
      "text": "tel\u00e9fono",
      "relevance": 0.462096,
      "count": 1
    },
    {
      "text": "Acuerdo",
      "relevance": 0.460135,
      "count": 1
    },
    {
      "text": "Marzo",
      "relevance": 0.458175,
      "count": 2
    },
    {
      "text": "TERCERO",
      "relevance": 0.458175,
      "count": 1
    },
    {
      "text": "Nombre",
      "relevance": 0.458175,
      "count": 1
    },
    {
      "text": "C\u00e9dula",
      "relevance": 0.458175,
      "count": 1
    },
    {
      "text": "Salario",
      "relevance": 0.458175,
      "count": 1
    },
    {
      "text": "Objeto",
      "relevance": 0.458175,
      "count": 1
    }
  ]
}