{
  "usage": {
    "text_units": 1,
    "text_characters": 2224,
    "features": 1
  },
  "language": "es",
  "keywords": [
    {
      "text": "GASTOS DE TRANSPORTE LOCAL",
      "relevance": 0.698555,
      "count": 3
    },
    {
      "text": "DECANO DE LA FACULTAD DE INGENIERIA",
      "relevance": 0.627126,
      "count": 1
    },
    {
      "text": "profesora PATRICIA TORRES",
      "relevance": 0.590682,
      "count": 2
    },
    {
      "text": "CONCEDE COMISION ACADEMICA",
      "relevance": 0.584867,
      "count": 1
    },
    {
      "text": "Estatuto General de la Universidad",
      "relevance": 0.584732,
      "count": 1
    },
    {
      "text": "Consejo Superior",
      "relevance": 0.581358,
      "count": 2
    },
    {
      "text": "PAGO DE VIATICOS",
      "relevance": 0.575069,
      "count": 1
    },
    {
      "text": "recursos de la Decanatura de la Facultad",
      "relevance": 0.56975,
      "count": 1
    },
    {
      "text": "uso de sus facultades legales",
      "relevance": 0.557196,
      "count": 1
    },
    {
      "text": "Visita t\u00e9cnica",
      "relevance": 0.551789,
      "count": 1
    },
    {
      "text": "anterior Comisi\u00e9n Acad\u00e9mica",
      "relevance": 0.533524,
      "count": 1
    },
    {
      "text": "Vicedecana de Investigaciones",
      "relevance": 0.519904,
      "count": 1
    },
    {
      "text": "problemas de lodos",
      "relevance": 0.519904,
      "count": 1
    },
    {
      "text": "Planta de la Empresa Colombina",
      "relevance": 0.517404,
      "count": 1
    },
    {
      "text": "gastos de vidticos",
      "relevance": 0.515336,
      "count": 1
    },
    {
      "text": "PESOS MCTE",
      "relevance": 0.510285,
      "count": 3
    },
    {
      "text": "gastos de transporte intermunicipal",
      "relevance": 0.504093,
      "count": 2
    },
    {
      "text": "COMISION ACADEMICA",
      "relevance": 0.503634,
      "count": 1
    },
    {
      "text": "trabajos conjuntos",
      "relevance": 0.499694,
      "count": 1
    },
    {
      "text": "Resoluci\u00e9n No",
      "relevance": 0.498701,
      "count": 1
    },
    {
      "text": "paragrafo",
      "relevance": 0.496205,
      "count": 1
    },
    {
      "text": "transporte local",
      "relevance": 0.492878,
      "count": 1
    },
    {
      "text": "Articulo",
      "relevance": 0.492085,
      "count": 2
    },
    {
      "text": "RO LOZANO MONCADA MONICA PIEDAD CONSUEGRA",
      "relevance": 0.487793,
      "count": 1
    },
    {
      "text": "Decanatura No",
      "relevance": 0.482673,
      "count": 1
    },
    {
      "text": "Consejo de Facultad",
      "relevance": 0.482057,
      "count": 1
    },
    {
      "text": "Objeto",
      "relevance": 0.480797,
      "count": 1
    },
    {
      "text": "CUAL",
      "relevance": 0.478645,
      "count": 1
    },
    {
      "text": "PTAR",
      "relevance": 0.47678,
      "count": 1
    },
    {
      "text": "GASTOS DE TRANSPORTE INTERMUNICIPAL A",
      "relevance": 0.475299,
      "count": 1
    }
  ]
}