{
  "usage": {
    "text_units": 1,
    "text_characters": 1122,
    "features": 1
  },
  "language": "es",
  "keywords": [
    {
      "text": "Laboratorios de Servicios",
      "relevance": 0.626507,
      "count": 1
    },
    {
      "text": "PESOS MCTE",
      "relevance": 0.579193,
      "count": 1
    },
    {
      "text": "toma de muestras",
      "relevance": 0.553729,
      "count": 1
    },
    {
      "text": "Laboratorios de Servicio",
      "relevance": 0.546581,
      "count": 1
    },
    {
      "text": "DANIEL ASCUNTAR Rios",
      "relevance": 0.536549,
      "count": 1
    },
    {
      "text": "DECANO DE LA FACULTAD DE INGENIERIA",
      "relevance": 0.534785,
      "count": 1
    },
    {
      "text": "CUAL",
      "relevance": 0.528684,
      "count": 1
    },
    {
      "text": "FACULTAD",
      "relevance": 0.527107,
      "count": 1
    },
    {
      "text": "PAGO DE GASTOS DE VIAJE",
      "relevance": 0.521141,
      "count": 1
    },
    {
      "text": "uso de sus facultades legales",
      "relevance": 0.514492,
      "count": 1
    },
    {
      "text": "Estatuto General de la Universidad",
      "relevance": 0.511769,
      "count": 1
    },
    {
      "text": "Articulo",
      "relevance": 0.501284,
      "count": 1
    },
    {
      "text": "CARLOS",
      "relevance": 0.501185,
      "count": 1
    },
    {
      "text": "DANIEL ASCUNTAR RiOS Gastos",
      "relevance": 0.499274,
      "count": 1
    },
    {
      "text": "DANIEL",
      "relevance": 0.493033,
      "count": 1
    },
    {
      "text": "gastos de viaje serdn",
      "relevance": 0.490897,
      "count": 1
    },
    {
      "text": "PAGO DE GASTOS DE VIAJE A",
      "relevance": 0.48871,
      "count": 1
    },
    {
      "text": "Escuela",
      "relevance": 0.484275,
      "count": 1
    },
    {
      "text": "tel\u00e9fono",
      "relevance": 0.484275,
      "count": 1
    },
    {
      "text": "Universidad",
      "relevance": 0.483532,
      "count": 1
    },
    {
      "text": "Acuerdo",
      "relevance": 0.480089,
      "count": 1
    },
    {
      "text": "valor",
      "relevance": 0.479592,
      "count": 1
    },
    {
      "text": "RiOS",
      "relevance": 0.478523,
      "count": 1
    },
    {
      "text": "cubiertos",
      "relevance": 0.477252,
      "count": 1
    },
    {
      "text": "Septiembre",
      "relevance": 0.474913,
      "count": 2
    },
    {
      "text": "Valle",
      "relevance": 0.474913,
      "count": 1
    },
    {
      "text": "TERCERO",
      "relevance": 0.474913,
      "count": 2
    },
    {
      "text": "Nombre",
      "relevance": 0.474913,
      "count": 1
    },
    {
      "text": "C\u00e9dula",
      "relevance": 0.474913,
      "count": 1
    },
    {
      "text": "Objeto",
      "relevance": 0.474913,
      "count": 1
    }
  ]
}