{
  "usage": {
    "text_units": 1,
    "text_characters": 1531,
    "features": 1
  },
  "language": "es",
  "keywords": [
    {
      "text": "literal fi del Articulo",
      "relevance": 0.723023,
      "count": 1
    },
    {
      "text": "DECANO DE LA FACULTAD DE INGENIERIA",
      "relevance": 0.665658,
      "count": 1
    },
    {
      "text": "PAGO DE GASTOS DE VIAJE",
      "relevance": 0.629325,
      "count": 2
    },
    {
      "text": "CARLOS AR",
      "relevance": 0.598416,
      "count": 1
    },
    {
      "text": "Consejo Superior",
      "relevance": 0.583967,
      "count": 1
    },
    {
      "text": "Ingeniero ANDRES FELIPE",
      "relevance": 0.580103,
      "count": 1
    },
    {
      "text": "GASTOS DE TRANSPORTE",
      "relevance": 0.569982,
      "count": 2
    },
    {
      "text": "uso de sus facultades legales",
      "relevance": 0.567876,
      "count": 1
    },
    {
      "text": "Estatuto General de la Universidad",
      "relevance": 0.561141,
      "count": 1
    },
    {
      "text": "ruta Cali",
      "relevance": 0.556245,
      "count": 1
    },
    {
      "text": "TIQUETE AEREO",
      "relevance": 0.552452,
      "count": 1
    },
    {
      "text": "recursos propios del Grupo",
      "relevance": 0.533793,
      "count": 1
    },
    {
      "text": "PESOS MCTE",
      "relevance": 0.52943,
      "count": 1
    },
    {
      "text": "Alta Tension",
      "relevance": 0.514863,
      "count": 1
    },
    {
      "text": "TIQUETE AEREO A",
      "relevance": 0.512058,
      "count": 1
    },
    {
      "text": "conceptode Gastos de Viaje",
      "relevance": 0.511409,
      "count": 1
    },
    {
      "text": "prueba de anilisis",
      "relevance": 0.510273,
      "count": 1
    },
    {
      "text": "Tiquete A\u00e9reo",
      "relevance": 0.495903,
      "count": 2
    },
    {
      "text": "personal de la empresa Codensa S. A. ESP",
      "relevance": 0.486161,
      "count": 1
    },
    {
      "text": "FACULTAD",
      "relevance": 0.484038,
      "count": 1
    },
    {
      "text": "Gastos de Viaje",
      "relevance": 0.475575,
      "count": 1
    },
    {
      "text": "sefior ANDRES FELIPE CERON PIAMBA",
      "relevance": 0.472832,
      "count": 1
    },
    {
      "text": "Objeto",
      "relevance": 0.471998,
      "count": 1
    },
    {
      "text": "respuesta",
      "relevance": 0.471998,
      "count": 1
    },
    {
      "text": "CUAL",
      "relevance": 0.471681,
      "count": 1
    },
    {
      "text": "Investigacion",
      "relevance": 0.466,
      "count": 1
    },
    {
      "text": "edificio",
      "relevance": 0.466,
      "count": 1
    },
    {
      "text": "cubiertos",
      "relevance": 0.46264,
      "count": 1
    },
    {
      "text": "Fecha",
      "relevance": 0.459696,
      "count": 1
    },
    {
      "text": "Nombre",
      "relevance": 0.459688,
      "count": 1
    }
  ]
}