{
  "usage": {
    "text_units": 1,
    "text_characters": 4787,
    "features": 1
  },
  "language": "es",
  "keywords": [
    {
      "text": "TOTAL SEDE BUGA",
      "relevance": 0.757676,
      "count": 1
    },
    {
      "text": "GRAN TOTAL",
      "relevance": 0.679223,
      "count": 1
    },
    {
      "text": "Arte Dramatico",
      "relevance": 0.652412,
      "count": 2
    },
    {
      "text": "Examen de Estado",
      "relevance": 0.652189,
      "count": 1
    },
    {
      "text": "siguiente Oferta Acad\u00e9mica",
      "relevance": 0.63284,
      "count": 1
    },
    {
      "text": "TOTAL SEDE PACIFICO",
      "relevance": 0.621431,
      "count": 1
    },
    {
      "text": "resultados del Examen de Estado",
      "relevance": 0.615488,
      "count": 3
    },
    {
      "text": "Sedes Regionales",
      "relevance": 0.581427,
      "count": 1
    },
    {
      "text": "Reglamento de Inscripci\u00e9n",
      "relevance": 0.577271,
      "count": 1
    },
    {
      "text": "Periodo Febrero-Junio",
      "relevance": 0.570667,
      "count": 1
    },
    {
      "text": "TOTAL SEDE YUMBO",
      "relevance": 0.570005,
      "count": 1
    },
    {
      "text": "Programas Acad\u00e9micos",
      "relevance": 0.569964,
      "count": 3
    },
    {
      "text": "Consejo Acad\u00e9mico",
      "relevance": 0.565566,
      "count": 4
    },
    {
      "text": "periodo acad\u00e9mico",
      "relevance": 0.556928,
      "count": 2
    },
    {
      "text": "Santiago de Cali",
      "relevance": 0.54563,
      "count": 1
    },
    {
      "text": "Tecnologia Agroambiental",
      "relevance": 0.543842,
      "count": 1
    },
    {
      "text": "Lenguas Extranjeras",
      "relevance": 0.5418,
      "count": 1
    },
    {
      "text": "Comercio Exterior",
      "relevance": 0.532481,
      "count": 1
    },
    {
      "text": "Licenciatura",
      "relevance": 0.525068,
      "count": 5
    },
    {
      "text": "excepcidn de la Tecnologia Agroambiental",
      "relevance": 0.516125,
      "count": 1
    },
    {
      "text": "resultados",
      "relevance": 0.510372,
      "count": 2
    },
    {
      "text": "Resoluciones del Consejo Acad\u00e9mico",
      "relevance": 0.507067,
      "count": 1
    },
    {
      "text": "Educaci\u00e9n Basica",
      "relevance": 0.503727,
      "count": 1
    },
    {
      "text": "Sistema de Regionalizaci\u00e9n de la Universidad",
      "relevance": 0.501343,
      "count": 2
    },
    {
      "text": "Mantenimiento de Equipo Portuario",
      "relevance": 0.498859,
      "count": 1
    },
    {
      "text": "Contaduria Publica",
      "relevance": 0.497583,
      "count": 3
    },
    {
      "text": "Logistica Portuaria",
      "relevance": 0.496551,
      "count": 1
    },
    {
      "text": "dias del mes de Octubre",
      "relevance": 0.496464,
      "count": 1
    },
    {
      "text": "anexos de la presente",
      "relevance": 0.496217,
      "count": 1
    },
    {
      "text": "Educacion Fisica",
      "relevance": 0.495628,
      "count": 1
    }
  ]
}