{
  "usage": {
    "text_units": 1,
    "text_characters": 1289,
    "features": 1
  },
  "language": "es",
  "keywords": [
    {
      "text": "DECANO DE LA FACULTAD DE INGENIERIA",
      "relevance": 0.792676,
      "count": 1
    },
    {
      "text": "Consejo Superior",
      "relevance": 0.653261,
      "count": 2
    },
    {
      "text": "literal fi del Articulo",
      "relevance": 0.606135,
      "count": 1
    },
    {
      "text": "facultades legales",
      "relevance": 0.580093,
      "count": 1
    },
    {
      "text": "anterior solicitud Acad\u00e9mica",
      "relevance": 0.579162,
      "count": 1
    },
    {
      "text": "retaria Consejo de Facultad",
      "relevance": 0.549284,
      "count": 1
    },
    {
      "text": "sesidn del dia martes",
      "relevance": 0.547373,
      "count": 1
    },
    {
      "text": "CONCEDE COMISION ACADEMICA",
      "relevance": 0.532251,
      "count": 1
    },
    {
      "text": "recursos de la Empresa Biocomfort",
      "relevance": 0.53099,
      "count": 1
    },
    {
      "text": "Estatuto General de la Universidad",
      "relevance": 0.528665,
      "count": 1
    },
    {
      "text": "gastos de transporte",
      "relevance": 0.525576,
      "count": 1
    },
    {
      "text": "correo electronico",
      "relevance": 0.517365,
      "count": 1
    },
    {
      "text": "Profesor CARLOS ALBERTO HERRERA CACERES",
      "relevance": 0.497616,
      "count": 1
    },
    {
      "text": "COMISION ACADEMICA A",
      "relevance": 0.489706,
      "count": 1
    },
    {
      "text": "CARLOS",
      "relevance": 0.46146,
      "count": 1
    },
    {
      "text": "TERCERO",
      "relevance": 0.460422,
      "count": 1
    },
    {
      "text": "CUAL",
      "relevance": 0.456194,
      "count": 1
    },
    {
      "text": "Nombre",
      "relevance": 0.455095,
      "count": 1
    },
    {
      "text": "Cargo",
      "relevance": 0.454514,
      "count": 1
    },
    {
      "text": "Facultad",
      "relevance": 0.453035,
      "count": 1
    },
    {
      "text": "viaticos",
      "relevance": 0.452329,
      "count": 1
    },
    {
      "text": "uso",
      "relevance": 0.449839,
      "count": 1
    },
    {
      "text": "Presentaci\u00e9n",
      "relevance": 0.448729,
      "count": 1
    },
    {
      "text": "Noviembre",
      "relevance": 0.448358,
      "count": 1
    },
    {
      "text": "paragrafo",
      "relevance": 0.446159,
      "count": 1
    },
    {
      "text": "Universidad",
      "relevance": 0.443903,
      "count": 1
    },
    {
      "text": "inscripcion",
      "relevance": 0.443903,
      "count": 1
    },
    {
      "text": "articulo",
      "relevance": 0.443703,
      "count": 1
    },
    {
      "text": "Consejo",
      "relevance": 0.44355,
      "count": 1
    },
    {
      "text": "Septiembre",
      "relevance": 0.442241,
      "count": 3
    }
  ]
}