{
  "usage": {
    "text_units": 1,
    "text_characters": 4220,
    "features": 1
  },
  "language": "es",
  "keywords": [
    {
      "text": "Virus del Papiloma Humano",
      "relevance": 0.61332,
      "count": 2
    },
    {
      "text": "implementacion de los estudios de la vacuna",
      "relevance": 0.603475,
      "count": 1
    },
    {
      "text": "revistas internacionales",
      "relevance": 0.5614,
      "count": 1
    },
    {
      "text": "Asociacion Internacional de Epidemiologia",
      "relevance": 0.557192,
      "count": 1
    },
    {
      "text": "motivo de orgullo",
      "relevance": 0.551406,
      "count": 1
    },
    {
      "text": "Doctora Munoz Calero",
      "relevance": 0.541285,
      "count": 1
    },
    {
      "text": "importante problema de salud",
      "relevance": 0.537666,
      "count": 1
    },
    {
      "text": "RESOLUCION No",
      "relevance": 0.537552,
      "count": 1
    },
    {
      "text": "dolor humano",
      "relevance": 0.536824,
      "count": 1
    },
    {
      "text": "liderazgo de la Doctora Munoz",
      "relevance": 0.534419,
      "count": 1
    },
    {
      "text": "excelencia acad\u00e9mica",
      "relevance": 0.534204,
      "count": 1
    },
    {
      "text": "Doctorado Honoris Causa",
      "relevance": 0.533811,
      "count": 1
    },
    {
      "text": "gran inter\u00e9s",
      "relevance": 0.531118,
      "count": 1
    },
    {
      "text": "distinci6n",
      "relevance": 0.530679,
      "count": 2
    },
    {
      "text": "m\u00e9trica favorita de los cientificos",
      "relevance": 0.530363,
      "count": 1
    },
    {
      "text": "presente Resolucion",
      "relevance": 0.529974,
      "count": 1
    },
    {
      "text": "criterios fundamentales",
      "relevance": 0.528864,
      "count": 1
    },
    {
      "text": "Merck Sharp",
      "relevance": 0.528401,
      "count": 1
    },
    {
      "text": "Jefe de una Unidad de Epidemiologia",
      "relevance": 0.527167,
      "count": 1
    },
    {
      "text": "Consejo Superior",
      "relevance": 0.525348,
      "count": 2
    },
    {
      "text": "miembro del comit\u00e9 directivo",
      "relevance": 0.524861,
      "count": 1
    },
    {
      "text": "ceremonia especial",
      "relevance": 0.522774,
      "count": 1
    },
    {
      "text": "cuello uterino",
      "relevance": 0.522001,
      "count": 1
    },
    {
      "text": "premio Nobel de Medicina",
      "relevance": 0.521526,
      "count": 1
    },
    {
      "text": "alto sentido de pertenencia",
      "relevance": 0.51943,
      "count": 1
    },
    {
      "text": "Universidad del Valle",
      "relevance": 0.51775,
      "count": 2
    },
    {
      "text": "titulo correspondiente",
      "relevance": 0.515384,
      "count": 1
    },
    {
      "text": "M\u00e9dica NUBIA MUNOZ CALERO",
      "relevance": 0.514378,
      "count": 2
    },
    {
      "text": "virus de la hepatitis",
      "relevance": 0.514027,
      "count": 1
    },
    {
      "text": "Cancer",
      "relevance": 0.513963,
      "count": 1
    }
  ]
}