{
  "usage": {
    "text_units": 1,
    "text_characters": 1793,
    "features": 1
  },
  "language": "es",
  "keywords": [
    {
      "text": "programa acad\u00e9mico",
      "relevance": 0.780875,
      "count": 1
    },
    {
      "text": "atribuciones legales",
      "relevance": 0.674093,
      "count": 1
    },
    {
      "text": "Consejo Directivo",
      "relevance": 0.625117,
      "count": 1
    },
    {
      "text": "plan de estudios conducente",
      "relevance": 0.624195,
      "count": 1
    },
    {
      "text": "Consejo Acad\u00e9mico",
      "relevance": 0.611718,
      "count": 1
    },
    {
      "text": "Ministerio de Educacion Nacional",
      "relevance": 0.606368,
      "count": 1
    },
    {
      "text": "titulo acad\u00e9mico",
      "relevance": 0.596593,
      "count": 1
    },
    {
      "text": "Santiago de Cali",
      "relevance": 0.587922,
      "count": 1
    },
    {
      "text": "Consejo Superior",
      "relevance": 0.564934,
      "count": 1
    },
    {
      "text": "programa acad\u00e9mico de ESPECIALIDAD",
      "relevance": 0.556704,
      "count": 1
    },
    {
      "text": "Salon de Reuniones del Despacho",
      "relevance": 0.541747,
      "count": 1
    },
    {
      "text": "programa acad\u00e9mico de ESPECIALIZACION",
      "relevance": 0.535901,
      "count": 1
    },
    {
      "text": "solicitud de Registro Calificado",
      "relevance": 0.526255,
      "count": 1
    },
    {
      "text": "Escuela de Medicina de la Facultad",
      "relevance": 0.526255,
      "count": 1
    },
    {
      "text": "literal b",
      "relevance": 0.514303,
      "count": 1
    },
    {
      "text": "Estatuto General",
      "relevance": 0.507858,
      "count": 1
    },
    {
      "text": "Programas de acuerdo",
      "relevance": 0.506868,
      "count": 1
    },
    {
      "text": "CONSEJO SUPERIOR DE LA UNIVERSIDAD DEL VALLE",
      "relevance": 0.500609,
      "count": 1
    },
    {
      "text": "dia de marzo",
      "relevance": 0.498832,
      "count": 1
    },
    {
      "text": "titulo de ESPECIALISTA",
      "relevance": 0.496456,
      "count": 1
    },
    {
      "text": "Resolucion No",
      "relevance": 0.489965,
      "count": 2
    },
    {
      "text": "Resoluci\u00e9n No",
      "relevance": 0.482389,
      "count": 1
    },
    {
      "text": "ANESTESIOLOGIA",
      "relevance": 0.471875,
      "count": 6
    },
    {
      "text": "Diciembre",
      "relevance": 0.471875,
      "count": 1
    },
    {
      "text": "Salud",
      "relevance": 0.470452,
      "count": 1
    },
    {
      "text": "UNICO",
      "relevance": 0.462555,
      "count": 1
    },
    {
      "text": "modific6",
      "relevance": 0.458829,
      "count": 1
    },
    {
      "text": "adscrito",
      "relevance": 0.457199,
      "count": 1
    },
    {
      "text": "Universidad",
      "relevance": 0.455047,
      "count": 3
    },
    {
      "text": "t\u00e9rmino",
      "relevance": 0.454346,
      "count": 1
    }
  ]
}