{
  "usage": {
    "text_units": 1,
    "text_characters": 1664,
    "features": 1
  },
  "language": "es",
  "keywords": [
    {
      "text": "anterior solicitud Acad\u00e9mica",
      "relevance": 0.742951,
      "count": 1
    },
    {
      "text": "Consejo Superior",
      "relevance": 0.722151,
      "count": 2
    },
    {
      "text": "CONCEDE COMISION ACADEMICA",
      "relevance": 0.619564,
      "count": 1
    },
    {
      "text": "Profesor Asistente",
      "relevance": 0.599366,
      "count": 1
    },
    {
      "text": "PAGO DE INSCRIPCION",
      "relevance": 0.579142,
      "count": 1
    },
    {
      "text": "Ingenieria de Sistemas",
      "relevance": 0.577773,
      "count": 1
    },
    {
      "text": "Santiago de Cali",
      "relevance": 0.559,
      "count": 1
    },
    {
      "text": "DECANO DE LA FACULTAD DE INGENIERIA",
      "relevance": 0.551757,
      "count": 1
    },
    {
      "text": "sesion del dia martes",
      "relevance": 0.544302,
      "count": 1
    },
    {
      "text": "COMISION ACADEMICA",
      "relevance": 0.518772,
      "count": 1
    },
    {
      "text": "PESOS MCTE",
      "relevance": 0.518151,
      "count": 1
    },
    {
      "text": "Revista Peerj",
      "relevance": 0.513658,
      "count": 1
    },
    {
      "text": "INSCRIPCION A",
      "relevance": 0.508768,
      "count": 1
    },
    {
      "text": "uso de sus facultades legales",
      "relevance": 0.504034,
      "count": 1
    },
    {
      "text": "fondos de la Escuela",
      "relevance": 0.502228,
      "count": 1
    },
    {
      "text": "Computaci6n",
      "relevance": 0.501729,
      "count": 1
    },
    {
      "text": "Resoluci\u00e9n No",
      "relevance": 0.498698,
      "count": 1
    },
    {
      "text": "Articulo",
      "relevance": 0.483737,
      "count": 4
    },
    {
      "text": "Semantics for Pubmed Central",
      "relevance": 0.481616,
      "count": 1
    },
    {
      "text": "CUAL",
      "relevance": 0.480607,
      "count": 1
    },
    {
      "text": "Lugar",
      "relevance": 0.478458,
      "count": 1
    },
    {
      "text": "Facultad",
      "relevance": 0.471898,
      "count": 1
    },
    {
      "text": "Estatuto General de la Universidad",
      "relevance": 0.471556,
      "count": 1
    },
    {
      "text": "costo",
      "relevance": 0.468971,
      "count": 1
    },
    {
      "text": "profesor VICTOR ANDRES BUCHELI GUERRERO",
      "relevance": 0.467945,
      "count": 2
    },
    {
      "text": "Objeto",
      "relevance": 0.464543,
      "count": 1
    },
    {
      "text": "paragrafo",
      "relevance": 0.46193,
      "count": 1
    },
    {
      "text": "Cargo",
      "relevance": 0.460856,
      "count": 1
    },
    {
      "text": "Consejo",
      "relevance": 0.459581,
      "count": 1
    },
    {
      "text": "Nombre",
      "relevance": 0.457128,
      "count": 1
    }
  ]
}