{
  "usage": {
    "text_units": 1,
    "text_characters": 3971,
    "features": 1
  },
  "language": "es",
  "keywords": [
    {
      "text": "FACULTAD DE CIENCIAS NATURALES",
      "relevance": 0.792543,
      "count": 1
    },
    {
      "text": "Total cupos Facultad",
      "relevance": 0.714669,
      "count": 1
    },
    {
      "text": "FACULTAD DE INGENIERIA",
      "relevance": 0.656118,
      "count": 1
    },
    {
      "text": "Tecnologia Quimica",
      "relevance": 0.606021,
      "count": 2
    },
    {
      "text": "Total cupos Facultad de Ciencias",
      "relevance": 0.591378,
      "count": 1
    },
    {
      "text": "EXACTAS CUPOS",
      "relevance": 0.586179,
      "count": 1
    },
    {
      "text": "FACULTAD DE HUMANIDADES",
      "relevance": 0.578052,
      "count": 1
    },
    {
      "text": "Sede de Cali",
      "relevance": 0.571631,
      "count": 2
    },
    {
      "text": "Lenguas Extranjeras",
      "relevance": 0.569638,
      "count": 2
    },
    {
      "text": "Ingenieria Topografica",
      "relevance": 0.560785,
      "count": 1
    },
    {
      "text": "Educaci\u00e9n Basica",
      "relevance": 0.555113,
      "count": 1
    },
    {
      "text": "cupos Instituto",
      "relevance": 0.549205,
      "count": 1
    },
    {
      "text": "Terapia Ocupacional",
      "relevance": 0.546376,
      "count": 1
    },
    {
      "text": "Comercio Exterior",
      "relevance": 0.546376,
      "count": 1
    },
    {
      "text": "CIENCIAS SOCIALES",
      "relevance": 0.545691,
      "count": 1
    },
    {
      "text": "TOTAL CUPOS",
      "relevance": 0.545079,
      "count": 1
    },
    {
      "text": "Estudios Politicos",
      "relevance": 0.544209,
      "count": 1
    },
    {
      "text": "siguiente Oferta Acad\u00e9mica",
      "relevance": 0.541825,
      "count": 1
    },
    {
      "text": "OFERTA de PROGRAMAS ACADEMICOS",
      "relevance": 0.540478,
      "count": 1
    },
    {
      "text": "Ciencias Naturales",
      "relevance": 0.534063,
      "count": 2
    },
    {
      "text": "CUPOS",
      "relevance": 0.532855,
      "count": 3
    },
    {
      "text": "Santiago de Cali",
      "relevance": 0.532009,
      "count": 1
    },
    {
      "text": "requisitos generales",
      "relevance": 0.529964,
      "count": 1
    },
    {
      "text": "FACULTAD DE SALUD",
      "relevance": 0.529703,
      "count": 2
    },
    {
      "text": "Ingenieria de Materiales",
      "relevance": 0.5292,
      "count": 1
    },
    {
      "text": "ARTES INTEGRADAS",
      "relevance": 0.526617,
      "count": 1
    },
    {
      "text": "Licenciatura",
      "relevance": 0.522447,
      "count": 10
    },
    {
      "text": "Salon de Sesiones del Consejo",
      "relevance": 0.519952,
      "count": 1
    },
    {
      "text": "cupos Facultad de Salud",
      "relevance": 0.519894,
      "count": 1
    },
    {
      "text": "FACULTAD DE CIENCIAS DE LA ADMINISTRACION",
      "relevance": 0.515508,
      "count": 1
    }
  ]
}