{
  "usage": {
    "text_units": 1,
    "text_characters": 1518,
    "features": 1
  },
  "language": "es",
  "keywords": [
    {
      "text": "DECANO DE LA FACULTAD DE INGENIERIA",
      "relevance": 0.783422,
      "count": 1
    },
    {
      "text": "literal fi del Articulo",
      "relevance": 0.640671,
      "count": 1
    },
    {
      "text": "Consejo Superior",
      "relevance": 0.634477,
      "count": 2
    },
    {
      "text": "uso de sus facultades legales",
      "relevance": 0.624725,
      "count": 1
    },
    {
      "text": "anterior solicitud Acad\u00e9mica",
      "relevance": 0.581147,
      "count": 1
    },
    {
      "text": "CULO PRIMERO",
      "relevance": 0.57777,
      "count": 1
    },
    {
      "text": "Realizar Taller",
      "relevance": 0.574296,
      "count": 1
    },
    {
      "text": "CONCEDE COMISION ACADEMICA",
      "relevance": 0.568429,
      "count": 1
    },
    {
      "text": "PAGO DE VIATICOS",
      "relevance": 0.564573,
      "count": 1
    },
    {
      "text": "marco del Proyecto Regalias",
      "relevance": 0.546649,
      "count": 1
    },
    {
      "text": "Estatuto General de la Universidad",
      "relevance": 0.529345,
      "count": 1
    },
    {
      "text": "dia martes",
      "relevance": 0.519511,
      "count": 1
    },
    {
      "text": "Proyecto Regalias Cauca",
      "relevance": 0.510331,
      "count": 1
    },
    {
      "text": "PESOS MCTE",
      "relevance": 0.506403,
      "count": 1
    },
    {
      "text": "Instituto Cinara",
      "relevance": 0.500404,
      "count": 1
    },
    {
      "text": "Resoluci\u00e9n No",
      "relevance": 0.49925,
      "count": 1
    },
    {
      "text": "TRANSPORTE A",
      "relevance": 0.497487,
      "count": 1
    },
    {
      "text": "COMISION ACADEMICA",
      "relevance": 0.497373,
      "count": 1
    },
    {
      "text": "Profesora INES RESTREPO TARQUINO",
      "relevance": 0.485158,
      "count": 2
    },
    {
      "text": "ARTI",
      "relevance": 0.482862,
      "count": 1
    },
    {
      "text": "URO LOZANO MONCADA MONICA PIEDAD CONSUEGRA C.",
      "relevance": 0.472699,
      "count": 1
    },
    {
      "text": "CUAL",
      "relevance": 0.468066,
      "count": 1
    },
    {
      "text": "Facultad",
      "relevance": 0.464157,
      "count": 1
    },
    {
      "text": "Buga",
      "relevance": 0.463639,
      "count": 1
    },
    {
      "text": "valor",
      "relevance": 0.463436,
      "count": 1
    },
    {
      "text": "QUINTO",
      "relevance": 0.462844,
      "count": 1
    },
    {
      "text": "TRANSPORTE",
      "relevance": 0.460413,
      "count": 3
    },
    {
      "text": "Cargo",
      "relevance": 0.459752,
      "count": 1
    },
    {
      "text": "Noviembre",
      "relevance": 0.458488,
      "count": 1
    },
    {
      "text": "Tulua",
      "relevance": 0.458036,
      "count": 1
    }
  ]
}