{
  "usage": {
    "text_units": 1,
    "text_characters": 1414,
    "features": 1
  },
  "language": "es",
  "keywords": [
    {
      "text": "literal fi del Articulo",
      "relevance": 0.703441,
      "count": 1
    },
    {
      "text": "DECANO DE LA FACULTAD DE INGENIERIA",
      "relevance": 0.677528,
      "count": 1
    },
    {
      "text": "AUTORIZA APOYO ECONOMICO",
      "relevance": 0.619661,
      "count": 1
    },
    {
      "text": "International Engineering Seminar",
      "relevance": 0.607022,
      "count": 1
    },
    {
      "text": "Programa Acad\u00e9mico",
      "relevance": 0.604692,
      "count": 1
    },
    {
      "text": "Escuela de Ingenieria El\u00e9ctrica",
      "relevance": 0.588028,
      "count": 1
    },
    {
      "text": "Santiago de Cali",
      "relevance": 0.575598,
      "count": 1
    },
    {
      "text": "recursos de la Decanatura de la facultad",
      "relevance": 0.574158,
      "count": 1
    },
    {
      "text": "Consejo Superior",
      "relevance": 0.573017,
      "count": 1
    },
    {
      "text": "apoyo econdmico",
      "relevance": 0.548378,
      "count": 2
    },
    {
      "text": "Estatuto General de la Universidad",
      "relevance": 0.538268,
      "count": 1
    },
    {
      "text": "APOYO ECONOMICO A",
      "relevance": 0.53221,
      "count": 1
    },
    {
      "text": "San Gil",
      "relevance": 0.531765,
      "count": 1
    },
    {
      "text": "siguiente evento",
      "relevance": 0.503822,
      "count": 1
    },
    {
      "text": "dias de agosto",
      "relevance": 0.492834,
      "count": 1
    },
    {
      "text": "Objeto",
      "relevance": 0.472115,
      "count": 1
    },
    {
      "text": "uso de sus facultades legales conferidas",
      "relevance": 0.469732,
      "count": 1
    },
    {
      "text": "Codigo",
      "relevance": 0.469648,
      "count": 1
    },
    {
      "text": "estudiante JUAN CAMILO CERON ARAMBURO",
      "relevance": 0.466704,
      "count": 2
    },
    {
      "text": "CUAL",
      "relevance": 0.464288,
      "count": 1
    },
    {
      "text": "Lugar",
      "relevance": 0.459788,
      "count": 1
    },
    {
      "text": "TERCERO",
      "relevance": 0.458657,
      "count": 1
    },
    {
      "text": "versidn",
      "relevance": 0.453017,
      "count": 1
    },
    {
      "text": "ponente",
      "relevance": 0.450734,
      "count": 1
    },
    {
      "text": "veintidds",
      "relevance": 0.450016,
      "count": 1
    },
    {
      "text": "Nombre",
      "relevance": 0.450002,
      "count": 1
    },
    {
      "text": "Yopal",
      "relevance": 0.449638,
      "count": 1
    },
    {
      "text": "valor",
      "relevance": 0.448454,
      "count": 1
    },
    {
      "text": "Ingenieria",
      "relevance": 0.447936,
      "count": 1
    },
    {
      "text": "Universidad",
      "relevance": 0.447862,
      "count": 1
    }
  ]
}