{
  "usage": {
    "text_units": 1,
    "text_characters": 1758,
    "features": 1
  },
  "language": "es",
  "keywords": [
    {
      "text": "DECANO DE LA FACULTAD DE INGENIERIA",
      "relevance": 0.701796,
      "count": 1
    },
    {
      "text": "GASTOS DE TRANSPORTE",
      "relevance": 0.613659,
      "count": 4
    },
    {
      "text": "CULO TERCERO",
      "relevance": 0.611857,
      "count": 1
    },
    {
      "text": "PAGO DE VIATICOS",
      "relevance": 0.607484,
      "count": 1
    },
    {
      "text": "Consejo Superior",
      "relevance": 0.600235,
      "count": 2
    },
    {
      "text": "CONCEDE COMISION ACADEMICA",
      "relevance": 0.584684,
      "count": 1
    },
    {
      "text": "uso de sus facultades legales",
      "relevance": 0.575644,
      "count": 1
    },
    {
      "text": "anterior solicitud Acad\u00e9mica",
      "relevance": 0.566098,
      "count": 1
    },
    {
      "text": "TIQUETE AEREO",
      "relevance": 0.559362,
      "count": 1
    },
    {
      "text": "fondos del grupo de Investigaci\u00e9n",
      "relevance": 0.544603,
      "count": 1
    },
    {
      "text": "Tiquete A\u00e9reo",
      "relevance": 0.532932,
      "count": 2
    },
    {
      "text": "Estatuto General de la Universidad",
      "relevance": 0.524812,
      "count": 1
    },
    {
      "text": "dia martes",
      "relevance": 0.515278,
      "count": 1
    },
    {
      "text": "PESOS MCTE",
      "relevance": 0.515009,
      "count": 2
    },
    {
      "text": "correo electr\u00e9nico",
      "relevance": 0.515009,
      "count": 1
    },
    {
      "text": "laruta Cali",
      "relevance": 0.513159,
      "count": 1
    },
    {
      "text": "COMISION ACADEMICA",
      "relevance": 0.498085,
      "count": 1
    },
    {
      "text": "empresas ABB",
      "relevance": 0.496764,
      "count": 1
    },
    {
      "text": "ART",
      "relevance": 0.491733,
      "count": 1
    },
    {
      "text": "Profesor Titular Escuela de Ingenieria El\u00e9ctrica",
      "relevance": 0.478888,
      "count": 1
    },
    {
      "text": "profesor GUILLERMO APONTE MAYCR",
      "relevance": 0.474257,
      "count": 1
    },
    {
      "text": "CUAL",
      "relevance": 0.471838,
      "count": 1
    },
    {
      "text": "Cargo",
      "relevance": 0.46481,
      "count": 1
    },
    {
      "text": "PAGO",
      "relevance": 0.463294,
      "count": 1
    },
    {
      "text": "Profesor GUILLERMO APONTE MAYOR",
      "relevance": 0.461747,
      "count": 1
    },
    {
      "text": "QUINTO",
      "relevance": 0.461084,
      "count": 1
    },
    {
      "text": "viaticos",
      "relevance": 0.458709,
      "count": 1
    },
    {
      "text": "Articulo",
      "relevance": 0.45859,
      "count": 2
    },
    {
      "text": "Facultad",
      "relevance": 0.456694,
      "count": 1
    },
    {
      "text": "Capital",
      "relevance": 0.45546,
      "count": 1
    }
  ]
}