{
  "usage": {
    "text_units": 1,
    "text_characters": 1889,
    "features": 1
  },
  "language": "es",
  "keywords": [
    {
      "text": "CONCEDE COMISION ACADEMICA",
      "relevance": 0.631697,
      "count": 1
    },
    {
      "text": "Consejo Superior",
      "relevance": 0.619624,
      "count": 2
    },
    {
      "text": "DECANO DE LA FACULTAD DE INGENIERIA",
      "relevance": 0.612284,
      "count": 1
    },
    {
      "text": "PESOS mcte",
      "relevance": 0.574755,
      "count": 3
    },
    {
      "text": "PAGO DE VIATICOS",
      "relevance": 0.558659,
      "count": 1
    },
    {
      "text": "anterior solicitud Acad\u00e9mica",
      "relevance": 0.550548,
      "count": 1
    },
    {
      "text": "local porun",
      "relevance": 0.536994,
      "count": 1
    },
    {
      "text": "Secretaria Consejo de Facultad",
      "relevance": 0.53646,
      "count": 1
    },
    {
      "text": "COMISION ACADEMICA",
      "relevance": 0.524773,
      "count": 1
    },
    {
      "text": "Santander de Quilichao",
      "relevance": 0.52299,
      "count": 1
    },
    {
      "text": "facultades legales",
      "relevance": 0.522276,
      "count": 1
    },
    {
      "text": "Estatuto Genera",
      "relevance": 0.511161,
      "count": 1
    },
    {
      "text": "Consejo de Facultad",
      "relevance": 0.507908,
      "count": 1
    },
    {
      "text": "Enero de 2019.FACULTAD",
      "relevance": 0.505736,
      "count": 1
    },
    {
      "text": "CARLOS",
      "relevance": 0.501562,
      "count": 1
    },
    {
      "text": "LOCAL E INTERDEPARTAMENTAL A",
      "relevance": 0.497739,
      "count": 1
    },
    {
      "text": "CUAL",
      "relevance": 0.490182,
      "count": 1
    },
    {
      "text": "PAGO",
      "relevance": 0.488074,
      "count": 1
    },
    {
      "text": "Acuerdo",
      "relevance": 0.485063,
      "count": 1
    },
    {
      "text": "O LOZANO MONCADA MONICA PIEDAD jo de Fault Cc",
      "relevance": 0.483394,
      "count": 1
    },
    {
      "text": "GASTOS",
      "relevance": 0.482816,
      "count": 5
    },
    {
      "text": "Proyecto Paz Alto Cauca Cl",
      "relevance": 0.480753,
      "count": 1
    },
    {
      "text": "VIATICOS",
      "relevance": 0.480448,
      "count": 1
    },
    {
      "text": "profesora IRENE VELEZ TORRES",
      "relevance": 0.479804,
      "count": 1
    },
    {
      "text": "Cargo",
      "relevance": 0.479278,
      "count": 1
    },
    {
      "text": "Lugar",
      "relevance": 0.475721,
      "count": 1
    },
    {
      "text": "recursos del Proyecto Paz Alto Cauca Cl",
      "relevance": 0.472139,
      "count": 1
    },
    {
      "text": "viadticos",
      "relevance": 0.470712,
      "count": 1
    },
    {
      "text": "QUINTO",
      "relevance": 0.470506,
      "count": 1
    },
    {
      "text": "Notificarala Profesora IRENE VELEZ TORRES",
      "relevance": 0.47006,
      "count": 1
    }
  ]
}